{
    "id": 123117,
    "name": "Ceratodon purpureus",
    "rank": "species",
    "source_id": 1,
    "created_at": "2012-01-15T07:31:04.235Z",
    "updated_at": "2019-11-08T11:56:41.708Z",
    "iconic_taxon_id": 47126,
    "is_iconic": false,
    "name_provider": "ColNameProvider",
    "observations_count": 6294,
    "listed_taxa_count": 5501,
    "rank_level": 10,
    "unique_name": "purpurstieliges hornzahnmoos",
    "wikipedia_summary": "<i><b>Ceratodon purpureus</b></i> is a dioicous moss with a color ranging from yellow-green to red. The height amounts to 3 centimeters. It is found worldwide, mainly in urban areas and next to roads on dry sand soils. It can grow in a very wide variety of habitats, from polluted highway shoulders and mine tailings to areas recently denuded by wildfire to the bright slopes of Antarctica. Its common names include <b>redshank</b>, <b>purple forkmoss</b>, <b>ceratodon moss</b>, <b>fire moss</b>,...",
    "wikipedia_title": null,
    "ancestry": "48460/47126/311249/48372/67877/67881/123116",
    "conservation_status": null,
    "conservation_status_source_id": null,
    "conservation_status_source_identifier": null,
    "is_active": true,
    "complete": null,
    "complete_rank": null,
    "taxon_framework_relationship_id": null,
    "uuid": "bddebe91-1193-4946-b131-5934fea22643",
    "photos_locked": false,
    "default_name": {
        "id": 774929,
        "name": "Redshank",
        "is_valid": true,
        "lexicon": "English"
    },
    "photo_url": "https://inaturalist-open-data.s3.amazonaws.com/photos/66975704/square.jpeg",
    "iconic_taxon_name": "Plantae",
    "conservation_status_name": null,
    "common_name": {
        "id": 774929,
        "name": "Redshank",
        "is_valid": true,
        "lexicon": "English"
    },
    "image_url": "https://inaturalist-open-data.s3.amazonaws.com/photos/66975704/square.jpeg",
    "taxon_range_kml_url": null,
    "html": null,
    "default_photo": {
        "id": 66975704,
        "user_id": 1690039,
        "native_photo_id": null,
        "created_at": "2020-04-14T21:09:49.757Z",
        "updated_at": "2020-04-14T21:09:49.757Z",
        "native_page_url": null,
        "native_username": null,
        "native_realname": null,
        "license": 2,
        "subtype": null,
        "native_original_image_url": null,
        "uuid": "80743d04-094e-488d-9c53-b5e2de1debb0",
        "file_extension_id": 2,
        "file_prefix_id": 1,
        "width": 2048,
        "height": 1365,
        "license_code": "CC-BY-NC",
        "license_name": "Creative Commons Attribution-NonCommercial License",
        "license_url": "http://creativecommons.org/licenses/by-nc/4.0/",
        "attribution": "(c) Kathy Webb + Bill Depew, some rights reserved (CC BY-NC), uploaded by Kathy Webb + Bill Depew",
        "type": "LocalPhoto",
        "square_url": "https://inaturalist-open-data.s3.amazonaws.com/photos/66975704/square.jpeg",
        "thumb_url": "https://inaturalist-open-data.s3.amazonaws.com/photos/66975704/thumb.jpeg",
        "small_url": "https://inaturalist-open-data.s3.amazonaws.com/photos/66975704/small.jpeg",
        "medium_url": "https://inaturalist-open-data.s3.amazonaws.com/photos/66975704/medium.jpeg",
        "large_url": "https://inaturalist-open-data.s3.amazonaws.com/photos/66975704/large.jpeg"
    },
    "created_at_utc": "2012-01-15T07:31:04.235Z",
    "updated_at_utc": "2019-11-08T11:56:41.708Z",
    "taxon_photos": [
        {
            "id": 875879,
            "taxon_id": 123117,
            "photo_id": 66975704,
            "position": 0,
            "created_at": "2020-05-19T14:07:04.711Z",
            "updated_at": "2020-05-19T14:07:04.711Z",
            "photo": {
                "id": 66975704,
                "user_id": 1690039,
                "native_photo_id": null,
                "created_at": "2020-04-14T21:09:49.757Z",
                "updated_at": "2020-04-14T21:09:49.757Z",
                "native_page_url": null,
                "native_username": null,
                "native_realname": null,
                "license": 2,
                "subtype": null,
                "native_original_image_url": null,
                "uuid": "80743d04-094e-488d-9c53-b5e2de1debb0",
                "file_extension_id": 2,
                "file_prefix_id": 1,
                "width": 2048,
                "height": 1365,
                "license_code": "CC-BY-NC",
                "attribution": "(c) Kathy Webb + Bill Depew, some rights reserved (CC BY-NC), uploaded by Kathy Webb + Bill Depew",
                "square_url": "https://inaturalist-open-data.s3.amazonaws.com/photos/66975704/square.jpeg",
                "thumb_url": "https://inaturalist-open-data.s3.amazonaws.com/photos/66975704/thumb.jpeg",
                "small_url": "https://inaturalist-open-data.s3.amazonaws.com/photos/66975704/small.jpeg",
                "medium_url": "https://inaturalist-open-data.s3.amazonaws.com/photos/66975704/medium.jpeg",
                "large_url": "https://inaturalist-open-data.s3.amazonaws.com/photos/66975704/large.jpeg",
                "license_name": "Creative Commons Attribution-NonCommercial License",
                "license_url": "http://creativecommons.org/licenses/by-nc/4.0/",
                "type": "LocalPhoto"
            }
        },
        {
            "id": 909175,
            "taxon_id": 123117,
            "photo_id": 63734017,
            "position": 1,
            "created_at": "2020-06-25T20:26:59.004Z",
            "updated_at": "2020-06-25T20:30:29.505Z",
            "photo": {
                "id": 63734017,
                "user_id": 2164172,
                "native_photo_id": null,
                "created_at": "2020-03-17T12:49:27.385Z",
                "updated_at": "2020-03-17T12:49:27.385Z",
                "native_page_url": null,
                "native_username": null,
                "native_realname": null,
                "license": 2,
                "subtype": null,
                "native_original_image_url": null,
                "uuid": "98531d66-8488-45b8-91cd-caaffed0c3f8",
                "file_extension_id": 2,
                "file_prefix_id": 1,
                "width": 1152,
                "height": 2048,
                "license_code": "CC-BY-NC",
                "attribution": "(c) Calum McLennan, some rights reserved (CC BY-NC), uploaded by Calum McLennan",
                "square_url": "https://inaturalist-open-data.s3.amazonaws.com/photos/63734017/square.jpeg",
                "thumb_url": "https://inaturalist-open-data.s3.amazonaws.com/photos/63734017/thumb.jpeg",
                "small_url": "https://inaturalist-open-data.s3.amazonaws.com/photos/63734017/small.jpeg",
                "medium_url": "https://inaturalist-open-data.s3.amazonaws.com/photos/63734017/medium.jpeg",
                "large_url": "https://inaturalist-open-data.s3.amazonaws.com/photos/63734017/large.jpeg",
                "license_name": "Creative Commons Attribution-NonCommercial License",
                "license_url": "http://creativecommons.org/licenses/by-nc/4.0/",
                "type": "LocalPhoto"
            }
        },
        {
            "id": 909174,
            "taxon_id": 123117,
            "photo_id": 57693336,
            "position": 2,
            "created_at": "2020-06-25T20:26:59.000Z",
            "updated_at": "2020-06-25T20:30:29.504Z",
            "photo": {
                "id": 57693336,
                "user_id": 830550,
                "native_photo_id": null,
                "created_at": "2019-12-09T06:30:00.717Z",
                "updated_at": "2019-12-09T06:30:00.717Z",
                "native_page_url": null,
                "native_username": null,
                "native_realname": null,
                "license": 2,
                "subtype": null,
                "native_original_image_url": null,
                "uuid": "767d60d8-c7f8-4b14-a038-7d71fe94ecdf",
                "file_extension_id": 1,
                "file_prefix_id": 1,
                "width": 1120,
                "height": 1400,
                "license_code": "CC-BY-NC",
                "attribution": "(c) Vladimir Bryukhov, some rights reserved (CC BY-NC), uploaded by Vladimir Bryukhov",
                "square_url": "https://inaturalist-open-data.s3.amazonaws.com/photos/57693336/square.jpg",
                "thumb_url": "https://inaturalist-open-data.s3.amazonaws.com/photos/57693336/thumb.jpg",
                "small_url": "https://inaturalist-open-data.s3.amazonaws.com/photos/57693336/small.jpg",
                "medium_url": "https://inaturalist-open-data.s3.amazonaws.com/photos/57693336/medium.jpg",
                "large_url": "https://inaturalist-open-data.s3.amazonaws.com/photos/57693336/large.jpg",
                "license_name": "Creative Commons Attribution-NonCommercial License",
                "license_url": "http://creativecommons.org/licenses/by-nc/4.0/",
                "type": "LocalPhoto"
            }
        },
        {
            "id": 359667,
            "taxon_id": 123117,
            "photo_id": 13006207,
            "position": 3,
            "created_at": "2018-02-03T18:39:27.815Z",
            "updated_at": "2020-06-25T20:30:29.502Z",
            "photo": {
                "id": 13006207,
                "user_id": null,
                "native_photo_id": "6099006351",
                "created_at": "2018-01-20T06:07:11.151Z",
                "updated_at": "2018-12-25T02:23:28.932Z",
                "native_page_url": "https://www.flickr.com/photos/22616984@N07/6099006351/",
                "native_username": "ibsut",
                "native_realname": "Ian Sutton",
                "license": 4,
                "subtype": "FlickrPhoto",
                "native_original_image_url": "https://farm7.staticflickr.com/6061/6099006351_2bde786c24_o.jpg",
                "uuid": "edf3af86-c88d-4ccc-8817-8b175524b67c",
                "file_extension_id": 1,
                "file_prefix_id": 1,
                "width": 1549,
                "height": 1130,
                "license_code": "CC-BY",
                "attribution": "(c) Ian Sutton, some rights reserved (CC BY)",
                "square_url": "https://inaturalist-open-data.s3.amazonaws.com/photos/13006207/square.jpg",
                "thumb_url": "https://inaturalist-open-data.s3.amazonaws.com/photos/13006207/thumb.jpg",
                "small_url": "https://inaturalist-open-data.s3.amazonaws.com/photos/13006207/small.jpg",
                "medium_url": "https://inaturalist-open-data.s3.amazonaws.com/photos/13006207/medium.jpg",
                "large_url": "https://inaturalist-open-data.s3.amazonaws.com/photos/13006207/large.jpg",
                "license_name": "Creative Commons Attribution License",
                "license_url": "http://creativecommons.org/licenses/by/4.0/",
                "type": "LocalPhoto"
            }
        },
        {
            "id": 909177,
            "taxon_id": 123117,
            "photo_id": 4816459,
            "position": 4,
            "created_at": "2020-06-25T20:26:59.011Z",
            "updated_at": "2020-06-25T20:30:29.505Z",
            "photo": {
                "id": 4816459,
                "user_id": 317047,
                "native_photo_id": null,
                "created_at": "2016-09-08T16:24:46.603Z",
                "updated_at": "2016-09-08T16:24:53.213Z",
                "native_page_url": null,
                "native_username": null,
                "native_realname": null,
                "license": 0,
                "subtype": null,
                "native_original_image_url": null,
                "uuid": "8e434f36-8844-4457-aefd-c16fd9b1c60c",
                "file_extension_id": 1,
                "file_prefix_id": 3,
                "width": 1536,
                "height": 2048,
                "license_code": "C",
                "attribution": "(c) Amanda Ring, all rights reserved, uploaded by Amanda Ring",
                "square_url": "http://static.inaturalist.org/photos/4816459/square.jpg",
                "thumb_url": "http://static.inaturalist.org/photos/4816459/thumb.jpg",
                "small_url": "http://static.inaturalist.org/photos/4816459/small.jpg",
                "medium_url": "http://static.inaturalist.org/photos/4816459/medium.jpg",
                "large_url": "http://static.inaturalist.org/photos/4816459/large.jpg",
                "license_name": "Copyright",
                "license_url": "http://en.wikipedia.org/wiki/Copyright",
                "type": "LocalPhoto"
            }
        },
        {
            "id": 909180,
            "taxon_id": 123117,
            "photo_id": 57853992,
            "position": 5,
            "created_at": "2020-06-25T20:26:59.024Z",
            "updated_at": "2020-06-25T20:30:29.508Z",
            "photo": {
                "id": 57853992,
                "user_id": 830550,
                "native_photo_id": null,
                "created_at": "2019-12-12T13:42:59.605Z",
                "updated_at": "2019-12-12T13:42:59.605Z",
                "native_page_url": null,
                "native_username": null,
                "native_realname": null,
                "license": 2,
                "subtype": null,
                "native_original_image_url": null,
                "uuid": "c881182b-585d-4ff5-926e-44267bf53a60",
                "file_extension_id": 1,
                "file_prefix_id": 1,
                "width": 1400,
                "height": 933,
                "license_code": "CC-BY-NC",
                "attribution": "(c) Vladimir Bryukhov, some rights reserved (CC BY-NC), uploaded by Vladimir Bryukhov",
                "square_url": "https://inaturalist-open-data.s3.amazonaws.com/photos/57853992/square.jpg",
                "thumb_url": "https://inaturalist-open-data.s3.amazonaws.com/photos/57853992/thumb.jpg",
                "small_url": "https://inaturalist-open-data.s3.amazonaws.com/photos/57853992/small.jpg",
                "medium_url": "https://inaturalist-open-data.s3.amazonaws.com/photos/57853992/medium.jpg",
                "large_url": "https://inaturalist-open-data.s3.amazonaws.com/photos/57853992/large.jpg",
                "license_name": "Creative Commons Attribution-NonCommercial License",
                "license_url": "http://creativecommons.org/licenses/by-nc/4.0/",
                "type": "LocalPhoto"
            }
        },
        {
            "id": 909176,
            "taxon_id": 123117,
            "photo_id": 63764610,
            "position": 6,
            "created_at": "2020-06-25T20:26:59.007Z",
            "updated_at": "2020-06-25T20:26:59.007Z",
            "photo": {
                "id": 63764610,
                "user_id": 898887,
                "native_photo_id": null,
                "created_at": "2020-03-17T20:22:10.359Z",
                "updated_at": "2020-03-17T20:22:10.359Z",
                "native_page_url": null,
                "native_username": null,
                "native_realname": null,
                "license": 2,
                "subtype": null,
                "native_original_image_url": null,
                "uuid": "020c3e04-11ba-48f4-970f-d6afee1578d8",
                "file_extension_id": 2,
                "file_prefix_id": 1,
                "width": 2048,
                "height": 1603,
                "license_code": "CC-BY-NC",
                "attribution": "(c) Bernd Bäumler, some rights reserved (CC BY-NC), uploaded by Bernd Bäumler",
                "square_url": "https://inaturalist-open-data.s3.amazonaws.com/photos/63764610/square.jpeg",
                "thumb_url": "https://inaturalist-open-data.s3.amazonaws.com/photos/63764610/thumb.jpeg",
                "small_url": "https://inaturalist-open-data.s3.amazonaws.com/photos/63764610/small.jpeg",
                "medium_url": "https://inaturalist-open-data.s3.amazonaws.com/photos/63764610/medium.jpeg",
                "large_url": "https://inaturalist-open-data.s3.amazonaws.com/photos/63764610/large.jpeg",
                "license_name": "Creative Commons Attribution-NonCommercial License",
                "license_url": "http://creativecommons.org/licenses/by-nc/4.0/",
                "type": "LocalPhoto"
            }
        },
        {
            "id": 909178,
            "taxon_id": 123117,
            "photo_id": 61919086,
            "position": 7,
            "created_at": "2020-06-25T20:26:59.015Z",
            "updated_at": "2020-06-25T20:30:29.506Z",
            "photo": {
                "id": 61919086,
                "user_id": 1453678,
                "native_photo_id": null,
                "created_at": "2020-02-21T23:06:53.916Z",
                "updated_at": "2020-02-21T23:06:53.916Z",
                "native_page_url": null,
                "native_username": null,
                "native_realname": null,
                "license": 2,
                "subtype": null,
                "native_original_image_url": null,
                "uuid": "d5607730-5f9c-4085-93e6-9aced419e720",
                "file_extension_id": 1,
                "file_prefix_id": 1,
                "width": 2037,
                "height": 2048,
                "license_code": "CC-BY-NC",
                "attribution": "(c) Marina Gorbunova, some rights reserved (CC BY-NC), uploaded by Marina Gorbunova",
                "square_url": "https://inaturalist-open-data.s3.amazonaws.com/photos/61919086/square.jpg",
                "thumb_url": "https://inaturalist-open-data.s3.amazonaws.com/photos/61919086/thumb.jpg",
                "small_url": "https://inaturalist-open-data.s3.amazonaws.com/photos/61919086/small.jpg",
                "medium_url": "https://inaturalist-open-data.s3.amazonaws.com/photos/61919086/medium.jpg",
                "large_url": "https://inaturalist-open-data.s3.amazonaws.com/photos/61919086/large.jpg",
                "license_name": "Creative Commons Attribution-NonCommercial License",
                "license_url": "http://creativecommons.org/licenses/by-nc/4.0/",
                "type": "LocalPhoto"
            }
        },
        {
            "id": 909179,
            "taxon_id": 123117,
            "photo_id": 14971045,
            "position": 8,
            "created_at": "2020-06-25T20:26:59.020Z",
            "updated_at": "2020-06-25T20:30:29.507Z",
            "photo": {
                "id": 14971045,
                "user_id": 791077,
                "native_photo_id": null,
                "created_at": "2018-04-09T00:04:42.478Z",
                "updated_at": "2018-04-09T00:04:42.478Z",
                "native_page_url": null,
                "native_username": null,
                "native_realname": null,
                "license": 2,
                "subtype": null,
                "native_original_image_url": null,
                "uuid": "261d7807-0501-4e49-a102-0724c321ddf1",
                "file_extension_id": 2,
                "file_prefix_id": 1,
                "width": 2048,
                "height": 1536,
                "license_code": "CC-BY-NC",
                "attribution": "(c) ajalat, some rights reserved (CC BY-NC), uploaded by ajalat",
                "square_url": "https://inaturalist-open-data.s3.amazonaws.com/photos/14971045/square.jpeg",
                "thumb_url": "https://inaturalist-open-data.s3.amazonaws.com/photos/14971045/thumb.jpeg",
                "small_url": "https://inaturalist-open-data.s3.amazonaws.com/photos/14971045/small.jpeg",
                "medium_url": "https://inaturalist-open-data.s3.amazonaws.com/photos/14971045/medium.jpeg",
                "large_url": "https://inaturalist-open-data.s3.amazonaws.com/photos/14971045/large.jpeg",
                "license_name": "Creative Commons Attribution-NonCommercial License",
                "license_url": "http://creativecommons.org/licenses/by-nc/4.0/",
                "type": "LocalPhoto"
            }
        }
    ],
    "taxon_names": [
        {
            "id": 2447864,
            "name": "Zęboróg purpurowy",
            "is_valid": true,
            "lexicon": "Polish",
            "taxon_id": 123117,
            "created_at": "2021-02-27T16:21:45.991Z",
            "updated_at": "2021-02-27T16:21:45.991Z",
            "creator_id": 472794,
            "position": 18,
            "parameterized_lexicon": "polish"
        },
        {
            "id": 783229,
            "name": "ヤノウエノアカゴケ",
            "is_valid": true,
            "lexicon": "Japanese",
            "taxon_id": 123117,
            "created_at": "2016-01-11T13:24:43.040Z",
            "updated_at": "2016-01-11T13:24:43.040Z",
            "creator_id": 37749,
            "position": 0,
            "parameterized_lexicon": "japanese"
        },
        {
            "id": 985835,
            "name": "Purpurstieliges Hornzahnmoos",
            "is_valid": true,
            "lexicon": "German",
            "taxon_id": 123117,
            "created_at": "2017-11-18T19:56:41.443Z",
            "updated_at": "2017-11-18T19:56:41.443Z",
            "creator_id": 5643,
            "position": 4,
            "parameterized_lexicon": "german"
        },
        {
            "id": 985836,
            "name": "Purpurmoos",
            "is_valid": true,
            "lexicon": "German",
            "taxon_id": 123117,
            "created_at": "2017-11-18T19:56:51.179Z",
            "updated_at": "2017-11-18T19:56:51.179Z",
            "creator_id": 5643,
            "position": 5,
            "parameterized_lexicon": "german"
        },
        {
            "id": 985837,
            "name": "Purpurstielzchen",
            "is_valid": true,
            "lexicon": "German",
            "taxon_id": 123117,
            "created_at": "2017-11-18T19:56:56.523Z",
            "updated_at": "2017-11-18T19:56:56.523Z",
            "creator_id": 5643,
            "position": 6,
            "parameterized_lexicon": "german"
        },
        {
            "id": 1728970,
            "name": "Paprastoji Rausvutė",
            "is_valid": true,
            "lexicon": "Lithuanian",
            "taxon_id": 123117,
            "created_at": "2019-09-17T09:27:44.348Z",
            "updated_at": "2019-09-17T09:27:44.348Z",
            "creator_id": 1244231,
            "position": 12,
            "parameterized_lexicon": "lithuanian"
        },
        {
            "id": 1777773,
            "name": "Цератодон пурпурный",
            "is_valid": true,
            "lexicon": "Russian",
            "taxon_id": 123117,
            "created_at": "2019-11-08T11:56:41.706Z",
            "updated_at": "2019-11-08T11:56:41.706Z",
            "creator_id": 1453678,
            "position": 13,
            "parameterized_lexicon": "russian"
        },
        {
            "id": 1926403,
            "name": "harilik punaharjak",
            "is_valid": true,
            "lexicon": "Estonian",
            "taxon_id": 123117,
            "created_at": "2020-01-16T10:36:09.926Z",
            "updated_at": "2020-01-16T10:36:09.926Z",
            "creator_id": 725720,
            "position": 14,
            "parameterized_lexicon": "estonian"
        },
        {
            "id": 2065271,
            "name": "brännmossa",
            "is_valid": true,
            "lexicon": "Swedish",
            "taxon_id": 123117,
            "created_at": "2020-05-06T13:28:54.218Z",
            "updated_at": "2020-05-06T13:28:54.218Z",
            "creator_id": 2041659,
            "position": 16,
            "parameterized_lexicon": "swedish"
        },
        {
            "id": 1195590,
            "name": "rohozub nachový",
            "is_valid": true,
            "lexicon": "Czech",
            "taxon_id": 123117,
            "created_at": "2018-04-26T19:49:33.319Z",
            "updated_at": "2018-04-26T19:49:33.319Z",
            "creator_id": null,
            "position": 7,
            "parameterized_lexicon": "czech"
        },
        {
            "id": 1593446,
            "name": "ugrasvegmose",
            "is_valid": true,
            "lexicon": "Norwegian",
            "taxon_id": 123117,
            "created_at": "2019-06-01T03:16:12.941Z",
            "updated_at": "2019-06-01T03:16:12.941Z",
            "creator_id": 1,
            "position": 10,
            "parameterized_lexicon": "norwegian"
        },
        {
            "id": 774929,
            "name": "Redshank",
            "is_valid": true,
            "lexicon": "English",
            "taxon_id": 123117,
            "created_at": "2015-11-26T17:19:55.515Z",
            "updated_at": "2015-11-26T17:19:55.515Z",
            "creator_id": 160,
            "position": 0,
            "parameterized_lexicon": "english"
        },
        {
            "id": 783405,
            "name": "Fire moss",
            "is_valid": true,
            "lexicon": "English",
            "taxon_id": 123117,
            "created_at": "2016-01-12T02:32:36.548Z",
            "updated_at": "2016-01-12T02:32:36.548Z",
            "creator_id": 37277,
            "position": 0,
            "parameterized_lexicon": "english"
        },
        {
            "id": 1490954,
            "name": "Purple Moss",
            "is_valid": true,
            "lexicon": "English",
            "taxon_id": 123117,
            "created_at": "2019-01-29T19:24:34.495Z",
            "updated_at": "2019-01-29T19:24:34.495Z",
            "creator_id": 564321,
            "position": 9,
            "parameterized_lexicon": "english"
        },
        {
            "id": 1305255,
            "name": "Rød horntand",
            "is_valid": true,
            "lexicon": "Danish",
            "taxon_id": 123117,
            "created_at": "2018-08-17T09:30:07.573Z",
            "updated_at": "2018-08-17T09:30:07.573Z",
            "creator_id": 477,
            "position": 8,
            "parameterized_lexicon": "danish"
        },
        {
            "id": 2001275,
            "name": "Gewoon purpersteeltje",
            "is_valid": true,
            "lexicon": "Dutch",
            "taxon_id": 123117,
            "created_at": "2020-03-18T22:16:33.924Z",
            "updated_at": "2020-03-18T22:16:33.924Z",
            "creator_id": 1,
            "position": 15,
            "parameterized_lexicon": "dutch"
        },
        {
            "id": 215603,
            "name": "Ceratodon purpureus",
            "is_valid": true,
            "lexicon": "Scientific Names",
            "taxon_id": 123117,
            "created_at": "2012-01-15T07:31:04.240Z",
            "updated_at": "2012-01-15T07:31:04.240Z",
            "creator_id": null,
            "position": 0,
            "parameterized_lexicon": "scientific-names"
        },
        {
            "id": 2897748,
            "name": "Dicranum purpureum",
            "is_valid": false,
            "lexicon": "Scientific Names",
            "taxon_id": 123117,
            "created_at": "2022-02-17T18:31:23.948Z",
            "updated_at": "2022-02-17T18:31:23.948Z",
            "creator_id": null,
            "position": 22,
            "parameterized_lexicon": "scientific-names"
        },
        {
            "id": 2194913,
            "name": "角齿藓",
            "is_valid": true,
            "lexicon": "Chinese (Simplified)",
            "taxon_id": 123117,
            "created_at": "2020-08-09T22:16:25.172Z",
            "updated_at": "2020-08-09T22:16:25.172Z",
            "creator_id": 1151287,
            "position": 17,
            "parameterized_lexicon": "chinese-simplified"
        },
        {
            "id": 1696665,
            "name": "metsäkulosammal",
            "is_valid": true,
            "lexicon": "Finnish",
            "taxon_id": 123117,
            "created_at": "2019-08-27T02:40:22.847Z",
            "updated_at": "2019-08-27T02:40:22.847Z",
            "creator_id": 1,
            "position": 11,
            "parameterized_lexicon": "finnish"
        },
        {
            "id": 2494586,
            "name": "Всюдник пурпуровий",
            "is_valid": true,
            "lexicon": "Ukrainian",
            "taxon_id": 123117,
            "created_at": "2021-03-29T11:40:22.693Z",
            "updated_at": "2021-03-29T11:40:22.693Z",
            "creator_id": 1961044,
            "position": 19,
            "parameterized_lexicon": "ukrainian"
        },
        {
            "id": 2527920,
            "name": "지붕빨간이끼",
            "is_valid": true,
            "lexicon": "Korean",
            "taxon_id": 123117,
            "created_at": "2021-05-03T12:50:33.898Z",
            "updated_at": "2021-05-03T12:50:33.898Z",
            "creator_id": 2027679,
            "position": 20,
            "parameterized_lexicon": "korean"
        },
        {
            "id": 2558257,
            "name": "cératodon pourpre",
            "is_valid": true,
            "lexicon": "French",
            "taxon_id": 123117,
            "created_at": "2021-05-30T21:48:43.757Z",
            "updated_at": "2021-05-30T21:48:43.757Z",
            "creator_id": 572540,
            "position": 21,
            "parameterized_lexicon": "french"
        }
    ],
    "iconic_taxon": {
        "id": 47126,
        "name": "Plantae"
    }
}